rigor/__init__.py
rigor/cli.py
rigor/collect.py
rigor/config.py
rigor/const.py
rigor/coverage.py
rigor/enums.py
rigor/execute.py
rigor/logging.py
rigor/metrics.py
rigor/model.py
rigor/namespace.py
rigor/pytest_plugin.py
rigor/reformat.py
rigor/reporting.py
rigor/session.py
rigor/state.py
rigor/swagger.py
rigor/utils.py
rigor/version.py
rigor/assets/cucumber-sandwich.jar
rigor-0.8.0.dist-info/LICENSE
rigor-0.8.0.dist-info/METADATA
rigor-0.8.0.dist-info/WHEEL
rigor-0.8.0.dist-info/entry_points.txt
rigor-0.8.0.dist-info/top_level.txt
rigor-0.8.0.dist-info/RECORD
