Metadata-Version: 2.1
Name: rigor
Version: 0.8.0
Summary: Rigor is a Domain Specific Language (DSL) and Command Line Interface (CLI) for making HTTP requests, extracting data, and validating responses. The main intent of Rigor is to be an HTTP-based API (e.g. REST) Testing Framework for automated functional or integration testing.
Author-email: Ian Maurer <ian@genomoncology.com>, Justin Yeakley <justin@genomoncology.com>
Classifier: Development Status :: 4 - Beta
Classifier: Intended Audience :: Developers
Classifier: License :: Other/Proprietary License
Classifier: Natural Language :: English
Classifier: Programming Language :: Python
Classifier: Programming Language :: Python :: 3.11
Requires-Python: >=3.11
License-File: LICENSE
Requires-Dist: addict
Requires-Dist: aiofiles
Requires-Dist: beautifulsoup4
Requires-Dist: click
Requires-Dist: colorama
Requires-Dist: httpx
Requires-Dist: hyperlink
Requires-Dist: importlib-metadata
Requires-Dist: jmespath
Requires-Dist: related
Requires-Dist: xlwt
Requires-Dist: structlog
Provides-Extra: dev
Requires-Dist: pytest ; extra == 'dev'
Requires-Dist: pytest-cov ; extra == 'dev'
Requires-Dist: pytest-asyncio ; extra == 'dev'
Requires-Dist: pytest-flake8 ; extra == 'dev'
Requires-Dist: pytest-pythonpath ; extra == 'dev'
Requires-Dist: pytest-sugar ; extra == 'dev'
Requires-Dist: pylint ; extra == 'dev'
Requires-Dist: flake8 ; extra == 'dev'
Requires-Dist: a2wsgi ; extra == 'dev'
Requires-Dist: starlette ; extra == 'dev'
Requires-Dist: coverage ; extra == 'dev'
Requires-Dist: tox ; extra == 'dev'
